{
  "fmc-syr4km937atxg6dx": {
    "reason": "already have a normal cut",
    "at": "2026-06-26T03:03:02.338Z"
  },
  "fmc-dsdm4l05kp4mobr1": {
    "reason": "already have a normal cut",
    "at": "2026-06-26T03:03:02.338Z"
  },
  "fmc-13o9jomdywes9b54": {
    "reason": "already have a normal cut",
    "at": "2026-06-26T03:03:02.338Z"
  },
  "fmc-43wd33qm20poy8zk": {
    "reason": "already have a normal cut",
    "at": "2026-06-26T03:03:02.338Z"
  },
  "fmc-0qmhxagaet0jv1v2": {
    "reason": "already have a normal cut",
    "at": "2026-06-26T03:03:02.338Z"
  },
  "fmc-wvqnttzv70qz332u": {
    "reason": "already have a normal cut",
    "at": "2026-06-26T03:03:02.339Z"
  },
  "fmc-iztr3u2y06z4cm5p": {
    "reason": "already have a normal cut",
    "at": "2026-06-26T03:03:02.339Z"
  },
  "fmc-o01cuyjq16w4vo8f": {
    "reason": "already have a normal cut",
    "at": "2026-06-26T03:03:02.339Z"
  },
  "fmc-nxtzecui0bwf0orv": {
    "reason": "already have a normal cut",
    "at": "2026-06-26T03:03:02.339Z"
  },
  "fmc-ope5wzquqc0ne2gl": {
    "reason": "already have a normal cut",
    "at": "2026-06-26T03:03:02.339Z"
  },
  "fmc-s0tkfty4s9049s0n": {
    "reason": "already have a normal cut",
    "at": "2026-06-26T03:03:02.339Z"
  },
  "fmc-lhlyg52nskctisfl": {
    "reason": "already have a normal cut",
    "at": "2026-06-26T03:03:02.340Z"
  }
}
